TokenCrypt/__init__.py
TokenCrypt/pkcs11.py
tokencrypt-0.1.2.dist-info/METADATA
tokencrypt-0.1.2.dist-info/WHEEL
tokencrypt-0.1.2.dist-info/top_level.txt
tokencrypt-0.1.2.dist-info/RECORD
