Metadata-Version: 2.1
Name: tokencrypt
Version: 0.1.2
Summary: PKCS11 Keys classes for cryptography
Home-page: https://github.com/rgammans/TokenCrypt
Author: Roger Gammans
Author-email: rgammans@gammascience.co.uk
License: UNKNOWN
Keywords: pkcs11 security cryptography
Platform: UNKNOWN
Classifier: Development Status :: 3 - Alpha
Classifier: Intended Audience :: Developers
Classifier: Topic :: Utilities
Classifier: Topic :: Security
Classifier: License :: OSI Approved :: MIT License
Classifier: Programming Language :: Python :: 3.6
Classifier: Programming Language :: Python :: 3.7
Requires-Python: >3.6.0
Requires-Dist: cryptography
Requires-Dist: PyKCS11
Provides-Extra: dev
Requires-Dist: pipenv ; extra == 'dev'
Provides-Extra: test
Requires-Dist: coverage ; extra == 'test'
